<?xml version="1.0" encoding="iso-8859-1"?>
<SUF70Messages>
<Language>
<Name>Italian</Name>
<Default>1</Default>
<Primary>16</Primary>
<Secondary>
<ID>1</ID>
<ID>2</ID>
</Secondary>
</Language>
<Messages>
<IDS_WINDOW_TITLE>%ProductName% Installazione</IDS_WINDOW_TITLE>
<IDS_HEADER_TEXT>Cartella di collegamento</IDS_HEADER_TEXT>
<IDS_SUBHEADER_TEXT>Dove vuoi installare i collegamenti?</IDS_SUBHEADER_TEXT>
<IDS_CTRL_BUTTON_NEXT>&amp;Avanti &gt;</IDS_CTRL_BUTTON_NEXT>
<IDS_CTRL_BUTTON_BACK>&lt; &amp;Indietro</IDS_CTRL_BUTTON_BACK>
<IDS_CTRL_BUTTON_CANCEL>A&amp;nnulla</IDS_CTRL_BUTTON_CANCEL>
<IDS_CTRL_BUTTON_HELP>Ai&amp;uto</IDS_CTRL_BUTTON_HELP>
<IDS_CTRL_STATICTEXT_TOPINSTRUCTIONS>Le icone di collegamento saranno create nel percorso sottostante. Se non vuoi usare la cartella predefinita, puoi scegliere di inserire un nuovo nome o selezionare una cartella esistente dalla lista.</IDS_CTRL_STATICTEXT_TOPINSTRUCTIONS>
<IDS_CTRL_STATICTEXT_LABEL_01>Cartella di collegamento:</IDS_CTRL_STATICTEXT_LABEL_01>
<IDS_CTRL_RADIOBTN_PERUSER>Installa i collegamenti solo per l'utente corrente</IDS_CTRL_RADIOBTN_PERUSER>
<IDS_CTRL_RADIOBTN_ALLUSERS>Rendi disponibili i collegamenti per tutti gli utenti</IDS_CTRL_RADIOBTN_ALLUSERS>
<IDS_CTRL_COMBOBOX_SHORTCUTFOLDERS>%AppShortcutFolderName%</IDS_CTRL_COMBOBOX_SHORTCUTFOLDERS>
</Messages>
</SUF70Messages>
